<?xml version="1.0" encoding="UTF-8"?>
<!DOCTYPE mapper PUBLIC "-//mybatis.org//DTD Mapper 3.0//EN" 
	"http://mybatis.org/dtd/mybatis-3-mapper.dtd">

<mapper namespace="board_sql">
	
	<select id="select_all" resultType="board">
		select 
			board.id, 
			board.title, 
			board.writer, 
			board.content, 
			board.wdate,
			user.username AS username,
			board.photoUrl
		from Board board, users user 
		<where>
			board.writer = user.id
		</where>
	</select>
	
	<select id="select" parameterType="board" resultType="board">
		select 
			board.id, 
			board.title, 
			board.writer, 
			board.content, 
			board.wdate,
			user.username AS username,
			board.photoUrl
		from Board board, users user 
		<where>
			board.writer = user.id
			<if test="search != null">
			and
			board.writer like '%${search}%'
			or
			board.title like '%${search}%'
			</if>
			order by board.id desc
			limit ${from}, ${to}
		</where>
	</select>
	
	<select id="select_one" parameterType="board" resultType="board">
		select 
			board.id, 
			board.title, 
			board.writer, 
			board.content, 
			board.wdate,
			user.username AS username,
			board.photoUrl
		from Board board, users user
		<where>
			board.id=${id}
			and board.writer = user.id
		</where>
	</select>
	
	<insert id="insert" parameterType="board">
		insert into Board 
		(title, writer, content, wdate, photoUrl)
		values
		('${title}', '${writer}', '${content}', NOW(), '${photoUrl}')
	</insert>
	
	<update id="update" parameterType="board">
		update Board
		<set>
			<if test="title != null">title='${title}',</if>
			<if test="content != null">content='${content}',</if>
		</set>
		<where>
			id=${id}
		</where>
	</update>
	
	<delete id="delete" parameterType="board">
		delete from Board
		where id = ${id}
	</delete>
</mapper>
